plsqlunwrap/__init__.py
plsqlunwrap/__main__.py
plsqlunwrap/unwrap.py
plsqlunwrap-0.0.2.dist-info/LICENSE
plsqlunwrap-0.0.2.dist-info/METADATA
plsqlunwrap-0.0.2.dist-info/WHEEL
plsqlunwrap-0.0.2.dist-info/entry_points.txt
plsqlunwrap-0.0.2.dist-info/top_level.txt
plsqlunwrap-0.0.2.dist-info/RECORD
