Metadata-Version: 2.1
Name: plsqlunwrap
Version: 0.0.2
Summary: A python utility package to unwrap Oracle wrapped objects.
Author-email: Lucas Rodrigues <git@lucas.rs>
License: Copyright 2023 Lucas Rodrigues
Project-URL: Homepage, https://github.com/plutaniano/plsqlunwrap
License-File: LICENSE
